aqute/__init__.py
aqute/engine.py
aqute/errors.py
aqute/py.typed
aqute/ratelimiter.py
aqute/task.py
aqute/worker.py
aqute-0.9.2.dist-info/LICENSE
aqute-0.9.2.dist-info/METADATA
aqute-0.9.2.dist-info/WHEEL
aqute-0.9.2.dist-info/RECORD
