Metadata-Version: 2.1
Name: aqute
Version: 0.9.2
Summary: Async QUeue Task Engine
Home-page: https://github.com/insomnes/aqute
License: MIT
Keywords: asyncio,producer-consumer,ratelimiting
Author: Mikhail Dengin
Author-email: denginm@gmail.com
Requires-Python: >=3.9,<4.0
Classifier: License :: OSI Approved :: MIT License
Classifier: Programming Language :: Python :: 3
Classifier: Programming Language :: Python :: 3.9
Classifier: Programming Language :: Python :: 3.10
Classifier: Programming Language :: Python :: 3.11
Classifier: Programming Language :: Python :: 3.12
Project-URL: Repository, https://github.com/insomnes/aqute
